{
  "_comment": "AI 블로그 글감 큐. 위에서부터 순서대로 사용됩니다. 새 항목을 추가하거나 빈 배열이 되면 GitHub Actions가 스킵합니다.",
  "topics": [
    {
      "title": "포지션의 힘 - 버튼이 가장 비싼 자리인 이유",
      "category": "strategy",
      "keywords": ["포지션", "버튼", "BTN", "EP MP LP", "포커 포지션 전략"],
      "angle": "9-맥스 테이블 기준 포지션별 EV 차이, 같은 핸드라도 포지션에 따라 달라지는 액션, 데이터로 본 포지션의 가치"
    },
    {
      "title": "C-Bet(컨티뉴에이션 베트) - 언제 쏘고 언제 멈춰야 하는가",
      "category": "strategy",
      "keywords": ["C-Bet", "컨티뉴에이션 베트", "플랍 전략", "베팅 빈도"],
      "angle": "보드 텍스처별 C-Bet 빈도, 사이즈 결정 원칙, 자주 하는 실수, 멀티웨이에서의 조정"
    },
    {
      "title": "스타팅 핸드 차트 - 169개 핸드 완벽 정리",
      "category": "strategy",
      "keywords": ["스타팅 핸드", "오프닝 핸드", "프리플랍 차트", "169 핸드"],
      "angle": "169개 가능한 시작 핸드의 등급, Sklansky 그룹, 포지션별 플레이 가능 핸드 매트릭스"
    },
    {
      "title": "블러프의 경제학 - 성공률 계산과 사이즈 결정",
      "category": "strategy",
      "keywords": ["블러프", "포커 블러프", "베팅 사이즈", "EV"],
      "angle": "블러프 손익분기점 계산법, 사이즈에 따른 폴드 빈도 요구치, 좋은 블러프 후보 선택법"
    },
    {
      "title": "토너먼트 ICM 입문 - 캐시 게임과 다른 결정 원리",
      "category": "strategy",
      "keywords": ["ICM", "토너먼트 전략", "버블 플레이", "스택 압력"],
      "angle": "ICM의 기본 원리, 버블 근처에서의 핸드 레인지 변화, 페이아웃 구조와 위험 회피"
    }
  ]
}
